tsql/__init__.py
tsql/cli.py
tsql/__pycache__/__init__.cpython-311.pyc
tsql/__pycache__/cli.cpython-311.pyc
tsql/classes/__init__.py
tsql/classes/app.py
tsql/classes/column.py
tsql/classes/database.py
tsql/classes/filter.py
tsql/classes/functions.py
tsql/classes/group.py
tsql/classes/table.py
tsql/classes/top_level.py
tsql/classes/__pycache__/__init__.cpython-311.pyc
tsql/classes/__pycache__/app.cpython-311.pyc
tsql/classes/__pycache__/column.cpython-311.pyc
tsql/classes/__pycache__/database.cpython-311.pyc
tsql/classes/__pycache__/filter.cpython-311.pyc
tsql/classes/__pycache__/functions.cpython-311.pyc
tsql/classes/__pycache__/group.cpython-311.pyc
tsql/classes/__pycache__/table.cpython-311.pyc
tsql/classes/__pycache__/top_level.cpython-311.pyc
tsql/templater/__init__.py
tsql/templater/templater.py
tsql/templater/__pycache__/__init__.cpython-311.pyc
tsql/templater/__pycache__/templater.cpython-311.pyc
tsql/templater/templates/__init__.py
tsql/templater/templates/classes.jinja
tsql/templater/templates/database.jinja
tsql/templater/templates/table.jinja
tsql/templater/templates/table_init.jinja
tsql_yaboiteedoh-0.4.0.dist-info/licenses/LICENSE
tsql_yaboiteedoh-0.4.0.dist-info/METADATA
tsql_yaboiteedoh-0.4.0.dist-info/WHEEL
tsql_yaboiteedoh-0.4.0.dist-info/entry_points.txt
tsql_yaboiteedoh-0.4.0.dist-info/top_level.txt
tsql_yaboiteedoh-0.4.0.dist-info/RECORD
