Metadata-Version: 2.4
Name: tsql-yaboiteedoh
Version: 0.4.0
Summary: Add your description here
Requires-Python: >=3.11.2
License-File: LICENSE
Requires-Dist: jinja2>=3.1.6
Requires-Dist: simple-term-menu>=1.6.6
Dynamic: license-file
